decel/__init__.py
decel-0.0.1.dist-info/LICENSE
decel-0.0.1.dist-info/WHEEL
decel-0.0.1.dist-info/METADATA
decel-0.0.1.dist-info/RECORD
